libhidet.so
libhidet_runtime.so
hidet/__init__.py
hidet/libinfo.py
hidet/logging.py
hidet/option.py
hidet/version.py
hidet/apps/compile_server/__init__.py
hidet/apps/compile_server/auth.py
hidet/apps/compile_server/compilation.py
hidet/apps/compile_server/core.py
hidet/apps/compile_server/user.py
hidet/backend/__init__.py
hidet/backend/build.py
hidet/backend/codegen.py
hidet/cli/__init__.py
hidet/cli/main.py
hidet/cli/bench/__init__.py
hidet/cli/bench/bench.py
hidet/cli/bench/bench_all.py
hidet/cli/bench/bench_common.py
hidet/cli/bench/model.py
hidet/cli/bench/nlp/__init__.py
hidet/cli/bench/nlp/models.py
hidet/cli/bench/nlp/nlp_model.py
hidet/cli/bench/vision/__init__.py
hidet/cli/bench/vision/inception_v3.py
hidet/cli/bench/vision/mobilenet_v2.py
hidet/cli/bench/vision/resnet.py
hidet/cli/bench/vision/resnext.py
hidet/cli/bench/vision/vision_model.py
hidet/cli/cache/__init__.py
hidet/cli/cache/clear.py
hidet/cli/cache/entry.py
hidet/cli/cache/status.py
hidet/cli/cache/utils.py
hidet/cuda/__init__.py
hidet/cuda/capability.py
hidet/cuda/device.py
hidet/cuda/event.py
hidet/cuda/graph.py
hidet/cuda/memory.py
hidet/cuda/stream.py
hidet/cuda/cublas/__init__.py
hidet/cuda/cublas/ffi.py
hidet/cuda/cublas/kernels.py
hidet/cuda/cublas/utils.py
hidet/cuda/cudnn/__init__.py
hidet/cuda/cudnn/benchmark.py
hidet/cuda/cudnn/ffi.py
hidet/cuda/cudnn/kernels.py
hidet/cuda/cudnn/utils.py
hidet/cuda/nccl/__init__.py
hidet/cuda/nccl/comm.py
hidet/cuda/nccl/ffi.py
hidet/cuda/nccl/libinfo.py
hidet/distributed/__init__.py
hidet/distributed/distributed.py
hidet/distributed/group.py
hidet/distributed/store.py
hidet/drivers/__init__.py
hidet/drivers/build_graph.py
hidet/drivers/build_module.py
hidet/drivers/build_task.py
hidet/drivers/utils.py
hidet/ffi/__init__.py
hidet/ffi/array.py
hidet/ffi/callbacks.py
hidet/ffi/convert.py
hidet/ffi/crt.py
hidet/ffi/ffi.py
hidet/ffi/runtime_api.py
hidet/ffi/shared_lib.py
hidet/ffi/utils.py
hidet/graph/__init__.py
hidet/graph/common.py
hidet-0.6.1.dist-info/licenses/LICENSE
hidet-0.6.1.dist-info/METADATA
hidet-0.6.1.dist-info/WHEEL
hidet-0.6.1.dist-info/entry_points.txt
hidet-0.6.1.dist-info/top_level.txt
hidet-0.6.1.dist-info/RECORD
