Metadata-Version: 2.4
Name: hidet
Version: 0.6.1
Summary: Hidet: a compilation-based DNN inference framework.
Author: CentML Inc.
License: Apache-2.0
Project-URL: Homepage, https://github.com/hidet-org/hidet
Project-URL: Documentation, https://hidet.org
Keywords: Deep Learning,Machine Learning,Neural Network,Inference,Compiler
Classifier: Development Status :: 4 - Beta
Classifier: Intended Audience :: Developers
Classifier: Intended Audience :: Education
Classifier: Intended Audience :: Science/Research
Classifier: License :: OSI Approved :: Apache Software License
Classifier: Topic :: Scientific/Engineering
Classifier: Topic :: Scientific/Engineering :: Mathematics
Classifier: Topic :: Scientific/Engineering :: Artificial Intelligence
Classifier: Topic :: Software Development
Classifier: Topic :: Software Development :: Libraries
Classifier: Topic :: Software Development :: Libraries :: Python Modules
Classifier: Programming Language :: C++
Classifier: Programming Language :: Python :: 3
Classifier: Operating System :: POSIX :: Linux
Requires-Python: >=3.9
License-File: LICENSE
Requires-Dist: numpy>=1.23
Requires-Dist: psutil
Requires-Dist: tabulate
Requires-Dist: tqdm
Requires-Dist: nvtx
Requires-Dist: click
Requires-Dist: packaging
Requires-Dist: requests
Requires-Dist: filelock
Requires-Dist: cuda-python>=11.6.1
Requires-Dist: hip-python-fork
Requires-Dist: lark
Requires-Dist: tomlkit
Requires-Dist: scipy
Requires-Dist: gitpython
Requires-Dist: importlib_metadata
Requires-Dist: torch>=2.3.0
Requires-Dist: networkx
Provides-Extra: dev
Requires-Dist: pytest==7.2; extra == "dev"
Requires-Dist: black==25.1.0; extra == "dev"
Requires-Dist: pylint==2.13.9; extra == "dev"
Requires-Dist: onnx; extra == "dev"
Requires-Dist: onnxruntime-gpu; extra == "dev"
Requires-Dist: torch>=2.3.0; extra == "dev"
Requires-Dist: torchvision; extra == "dev"
Requires-Dist: torchaudio; extra == "dev"
Requires-Dist: datasets; extra == "dev"
Requires-Dist: diffusers; extra == "dev"
Requires-Dist: transformers; extra == "dev"
Requires-Dist: sentencepiece; extra == "dev"
Requires-Dist: sacremoses; extra == "dev"
Requires-Dist: accelerate; extra == "dev"
Requires-Dist: pygraphviz; extra == "dev"
Requires-Dist: einops; extra == "dev"
Dynamic: license-file
